strainchoosr/__init__.py
strainchoosr/strainchoosr.py
strainchoosr/strainchoosr_gui.py
strainchoosr-0.1.6.dist-info/LICENSE
strainchoosr-0.1.6.dist-info/METADATA
strainchoosr-0.1.6.dist-info/WHEEL
strainchoosr-0.1.6.dist-info/entry_points.txt
strainchoosr-0.1.6.dist-info/top_level.txt
strainchoosr-0.1.6.dist-info/RECORD
