Metadata-Version: 2.1
Name: strainchoosr
Version: 0.1.6
Summary: This package was originally created by Andrew Low. Now maintained by Adam Koziol.
Home-page: https://github.com/OLC-Bioinformatics/StrainChoosr
Author: Adam Koziol
Author-email: adam.koziol@inspection.gc.ca
License-File: LICENSE
Requires-Dist: atomicwrites ==1.4.1
Requires-Dist: attrs ==23.2.0
Requires-Dist: ete3 ==3.1.3
Requires-Dist: more-itertools ==10.2.0
Requires-Dist: numpy ==1.26.4
Requires-Dist: pathlib2 ==2.3.7.post1
Requires-Dist: pluggy ==1.5.0
Requires-Dist: py ==1.11.0
Requires-Dist: PyQt5 ==5.15.10
Requires-Dist: pytest ==8.2.0
